<?xml version="1.0" standalone="yes"?><ns1:effect xmlns:ns1="ExcelLoading">
	<ns1:repetative>
		<ns1:name>celebration</ns1:name>
		<ns1:type>speed</ns1:type>
	</ns1:repetative>
	<ns1:repetative>
		<ns1:name>harvesting</ns1:name>
		<ns1:type>speed</ns1:type>
	</ns1:repetative>
	<ns1:repetative>
		<ns1:name>hunt</ns1:name>
		<ns1:type>speed</ns1:type>
	</ns1:repetative>
	<ns1:repetative>
		<ns1:name>butchering</ns1:name>
		<ns1:type>speed</ns1:type>
	</ns1:repetative>
	<ns1:repetative>
		<ns1:name>sewing</ns1:name>
		<ns1:type>speed</ns1:type>
	</ns1:repetative>
	<ns1:repetative>
		<ns1:name>log_cutting</ns1:name>
		<ns1:type>speed</ns1:type>
	</ns1:repetative>
	<ns1:repetative>
		<ns1:name>masonry</ns1:name>
		<ns1:type>speed</ns1:type>
	</ns1:repetative>
	<ns1:repetative>
		<ns1:name>carpentry</ns1:name>
		<ns1:type>speed</ns1:type>
	</ns1:repetative>
	<ns1:repetative>
		<ns1:name>bone_carving</ns1:name>
		<ns1:type>speed</ns1:type>
	</ns1:repetative>
	<ns1:repetative>
		<ns1:name>attack</ns1:name>
		<ns1:type>speed</ns1:type>
	</ns1:repetative>
	<ns1:repetative>
		<ns1:name>protection</ns1:name>
		<ns1:type>speed</ns1:type>
	</ns1:repetative>
	<ns1:repetative>
		<ns1:name>attack_distance</ns1:name>
		<ns1:type>speed</ns1:type>
	</ns1:repetative>
	<ns1:repetative>
		<ns1:name>building</ns1:name>
		<ns1:type>speed</ns1:type>
	</ns1:repetative>
	<ns1:repetative>
		<ns1:name>happy</ns1:name>
		<ns1:type>speed</ns1:type>
	</ns1:repetative>
	<ns1:repetative>
		<ns1:name>musicant</ns1:name>
		<ns1:type>speed</ns1:type>
	</ns1:repetative>
	<ns1:repetative>
		<ns1:name>animal_food</ns1:name>
		<ns1:type>speed</ns1:type>
	</ns1:repetative>
	<ns1:repetative>
		<ns1:name>food</ns1:name>
		<ns1:type>speed</ns1:type>
	</ns1:repetative>
	<ns1:repetative>
		<ns1:name>maxHappy</ns1:name>
		<ns1:type>speed</ns1:type>
	</ns1:repetative>
	<ns1:repetative>
		<ns1:name>cooking</ns1:name>
		<ns1:type>speed</ns1:type>
	</ns1:repetative>
	<ns1:repetative>
		<ns1:name>pottery</ns1:name>
		<ns1:type>speed</ns1:type>
	</ns1:repetative>
	<ns1:repetative>
		<ns1:name>plowing</ns1:name>
		<ns1:type>speed</ns1:type>
	</ns1:repetative>
	<ns1:repetative>
		<ns1:name>sow</ns1:name>
		<ns1:type>speed</ns1:type>
	</ns1:repetative>
	<ns1:repetative>
		<ns1:name>milling</ns1:name>
		<ns1:type>speed</ns1:type>
	</ns1:repetative>
	<ns1:repetative>
		<ns1:name>grow</ns1:name>
		<ns1:type>result</ns1:type>
	</ns1:repetative>
	<ns1:repetative>
		<ns1:name>living</ns1:name>
		<ns1:type>storage</ns1:type>
	</ns1:repetative>
	<ns1:repetative>
		<ns1:name>light_storage</ns1:name>
		<ns1:type>storage</ns1:type>
	</ns1:repetative>
	<ns1:repetative>
		<ns1:name>heavy_storage</ns1:name>
		<ns1:type>storage</ns1:type>
	</ns1:repetative>
	<ns1:repetative>
		<ns1:name>territory</ns1:name>
		<ns1:type>storage</ns1:type>
	</ns1:repetative>
	<ns1:repetative>
		<ns1:name>big_animal</ns1:name>
		<ns1:type>storage</ns1:type>
	</ns1:repetative>
	<ns1:repetative>
		<ns1:name>small_animal</ns1:name>
		<ns1:type>storage</ns1:type>
	</ns1:repetative>
</ns1:effect>